aether/__init__.py
aether/python/__init__.py
aether/python/constants.py
aether/python/exceptions.py
aether/python/utils.py
aether/python/validators.py
aether/python/avro/__init__.py
aether/python/avro/generation.py
aether/python/avro/normalization.py
aether/python/avro/schema.py
aether/python/avro/tools.py
aether/python/entity/__init__.py
aether/python/entity/extractor.py
aether/python/redis/__init__.py
aether/python/redis/task.py
aether.python-1.3.0.dist-info/LICENSE
aether.python-1.3.0.dist-info/METADATA
aether.python-1.3.0.dist-info/WHEEL
aether.python-1.3.0.dist-info/top_level.txt
aether.python-1.3.0.dist-info/RECORD
