Metadata-Version: 2.1
Name: aether.python
Version: 1.3.0
Summary: A python library with Aether Python functionality
Home-page: https://github.com/eHealthAfrica/aether-python-library/
Author: eHealth Africa
Author-email: aether@ehealthafrica.org
License: Apache2 License
Keywords: aether,entity,extraction,redis,utils,validators
Platform: UNKNOWN
Classifier: Development Status :: 4 - Beta
Classifier: Environment :: Plugins
Classifier: Intended Audience :: Developers
Classifier: License :: OSI Approved :: Apache Software License
Classifier: Natural Language :: English
Classifier: Operating System :: OS Independent
Classifier: Programming Language :: Python :: 3 :: Only
Classifier: Topic :: Software Development :: Libraries :: Python Modules
Requires-Python: >=3.7
Requires-Dist: avro-python3
Requires-Dist: eha-jsonpath
Requires-Dist: jsonschema
Requires-Dist: redis
Requires-Dist: requests[security]
Requires-Dist: spavro
Provides-Extra: test
Requires-Dist: birdisle ; extra == 'test'
Requires-Dist: coverage ; extra == 'test'
Requires-Dist: flake8 ; extra == 'test'
Requires-Dist: flake8-quotes ; extra == 'test'
Requires-Dist: tblib ; extra == 'test'
